cffi_magic/__init__.py
cffi_magic-0.0.9.dist-info/LICENSE
cffi_magic-0.0.9.dist-info/WHEEL
cffi_magic-0.0.9.dist-info/METADATA
cffi_magic-0.0.9.dist-info/RECORD
