Metadata-Version: 1.2
Name: cffi_magic
Version: 0.0.9
Summary: A module that define a cffi magic for IPython
Home-page: https://github.com/Carreau/cffi_magic
License: UNKNOWN
Author: Matthias Bussonnier
Author-email: bussonniermatthias@gmail.com
Classifier: License :: OSI Approved :: MIT License
Requires-Dist: cffi
